rsonpy-0.1.1.dist-info/METADATA
rsonpy-0.1.1.dist-info/WHEEL
rsonpy-0.1.1.dist-info/licenses/LICENSE
rsonpy/__init__.py
rsonpy/rsonpy.abi3.so
rsonpy/tests/data/test.json
rsonpy/tests/test_rsonpy.py
rsonpy-0.1.1.dist-info/RECORD
