Metadata-Version: 2.4
Name: rsonpy
Version: 0.1.1
Classifier: Programming Language :: Rust
Classifier: Programming Language :: Python :: Implementation :: CPython
Requires-Dist: pytest>=7.0 ; extra == 'dev'
Requires-Dist: pytest-cov>=4.0 ; extra == 'dev'
Provides-Extra: dev
License-File: LICENSE
Keywords: Json,Jsonpath,Rsonpath
Author-email: Charles Paperman <charles.paperman@univ-lille.fr>
Requires-Python: >=3.8
